g3core/__init__.py
g3core/_g3core.py
g3core/py.typed
g3core/file/__init__.py
g3core/file/_base_file.py
g3core/file/_fun_file.py
g3core/file/_typ_file.py
g3core/file_system/__init__.py
g3core/file_system/_file_system.py
g3core/st_parser/__init__.py
g3core/st_parser/_st_base_structure.py
g3core/st_parser/_st_enum.py
g3core/st_parser/_st_func.py
g3core/st_parser/_st_struct.py
g3core/st_parser/_st_var.py
g3core-0.2.0.dist-info/LICENCE
g3core-0.2.0.dist-info/METADATA
g3core-0.2.0.dist-info/WHEEL
g3core-0.2.0.dist-info/top_level.txt
g3core-0.2.0.dist-info/RECORD
